bayse_summary/__init__.py
bayse_summary/networktraffic_2022Feb12.1900UTC_filtered.bf
bayse_summary/networktraffic_2022Feb19.1900UTC_filtered.bf
bayse_summary/summarize.py
bayse_summary-1.0.3.dist-info/LICENSE
bayse_summary-1.0.3.dist-info/METADATA
bayse_summary-1.0.3.dist-info/WHEEL
bayse_summary-1.0.3.dist-info/top_level.txt
bayse_summary-1.0.3.dist-info/RECORD
