Metadata-Version: 2.1
Name: bayse-summary
Version: 1.0.3
Summary: Takes one or more BayseFlow files and summarizes them by the BayseFlows that are N-S or S-N.
Home-page: https://github.com/BayseIntelligence/bayseflow_summary
Author: Bayse, Inc.
Author-email: david@bayse.io
Project-URL: Bug Tracker, https://github.com/BayseIntelligence/bayseflow_summary/issues
Classifier: Programming Language :: Python :: 3
Classifier: License :: OSI Approved :: MIT License
Classifier: Operating System :: MacOS :: MacOS X
Classifier: Operating System :: POSIX :: Linux
Requires-Python: >=3.9
License-File: LICENSE
Requires-Dist: ipaddress (>=1.0.23)
Requires-Dist: pathlib (>=1.0.1)
Requires-Dist: python-dateutil (>=2.8.2)
Requires-Dist: python-magic (>=0.4.24)
Requires-Dist: requests (>=2.27.1)
Requires-Dist: six (>=1.16.0)
Requires-Dist: urllib3 (>=1.26.6)
Requires-Dist: jsonify (>=0.5)
Requires-Dist: argparse (>=1.4.0)
Requires-Dist: validators (>=0.20.0)
